git_auto_switch/__init__.py
git_auto_switch/cli.py
git_auto_switch/scripts/git-auto-switch
git_auto_switch/scripts/lib/applicators/git.sh
git_auto_switch/scripts/lib/applicators/hooks.sh
git_auto_switch/scripts/lib/applicators/remotes.sh
git_auto_switch/scripts/lib/applicators/ssh.sh
git_auto_switch/scripts/lib/cli/help.sh
git_auto_switch/scripts/lib/cli/router.sh
git_auto_switch/scripts/lib/commands/add.sh
git_auto_switch/scripts/lib/commands/apply.sh
git_auto_switch/scripts/lib/commands/audit.sh
git_auto_switch/scripts/lib/commands/current.sh
git_auto_switch/scripts/lib/commands/init.sh
git_auto_switch/scripts/lib/commands/list.sh
git_auto_switch/scripts/lib/commands/remove.sh
git_auto_switch/scripts/lib/commands/validate.sh
git_auto_switch/scripts/lib/core/constants.sh
git_auto_switch/scripts/lib/core/logger.sh
git_auto_switch/scripts/lib/core/utils.sh
git_auto_switch/scripts/lib/generators/git_config.sh
git_auto_switch/scripts/lib/generators/hooks.sh
git_auto_switch/scripts/lib/generators/ssh_config.sh
git_auto_switch/scripts/lib/state/account.sh
git_auto_switch/scripts/lib/state/state.sh
git_auto_switch-0.1.0.dist-info/licenses/LICENSE
git_auto_switch-0.1.0.dist-info/METADATA
git_auto_switch-0.1.0.dist-info/WHEEL
git_auto_switch-0.1.0.dist-info/entry_points.txt
git_auto_switch-0.1.0.dist-info/top_level.txt
git_auto_switch-0.1.0.dist-info/RECORD
