Metadata-Version: 2.4
Name: git-auto-switch
Version: 0.1.0
Summary: Manage multiple GitHub accounts with automatic identity switching based on workspace folders
Author-email: luongnv89 <luongnv89@gmail.com>
License-Expression: MIT
Project-URL: Homepage, https://github.com/luongnv89/git-auto-switch
Project-URL: Repository, https://github.com/luongnv89/git-auto-switch
Project-URL: Issues, https://github.com/luongnv89/git-auto-switch/issues
Keywords: git,github,ssh,multi-account,identity,cli
Classifier: Development Status :: 4 - Beta
Classifier: Environment :: Console
Classifier: Intended Audience :: Developers
Classifier: Operating System :: MacOS
Classifier: Operating System :: POSIX :: Linux
Classifier: Programming Language :: Unix Shell
Classifier: Topic :: Software Development :: Version Control :: Git
Requires-Python: >=3.7
License-File: LICENSE
Dynamic: license-file
